bayeslibs/__init__.py
bayeslibs/config/__init__.py
bayeslibs/config/apollo.yaml
bayeslibs/config/const.py
bayeslibs/config/setting.py
bayeslibs/motion/__init__.py
bayeslibs/motion/move/__init__.py
bayeslibs/motion/move/move.py
bayeslibs/motion/move/rotate.py
bayeslibs/motion/navigate/__init__.py
bayeslibs/motion/navigate/auto_nav.py
bayeslibs/samples/__init__.py
bayeslibs/samples/config.py
bayeslibs/samples/chapter4/__init__.py
bayeslibs/samples/chapter4/chapter4_1.py
bayeslibs/samples/chapter4/chapter4_10.py
bayeslibs/samples/chapter4/chapter4_11.py
bayeslibs/samples/chapter4/chapter4_12.py
bayeslibs/samples/chapter4/chapter4_13.py
bayeslibs/samples/chapter4/chapter4_2.py
bayeslibs/samples/chapter4/chapter4_3.py
bayeslibs/samples/chapter4/chapter4_4.py
bayeslibs/samples/chapter4/chapter4_5.py
bayeslibs/samples/chapter4/chapter4_6.py
bayeslibs/samples/chapter4/chapter4_7.py
bayeslibs/samples/chapter4/chapter4_8.py
bayeslibs/samples/chapter4/chapter4_9.py
bayeslibs/samples/chapter5/__init__.py
bayeslibs/samples/chapter5/chapter5_1.py
bayeslibs/samples/chapter5/chapter5_2.py
bayeslibs/samples/chapter5/chapter5_3.py
bayeslibs/samples/chapter5/chapter5_4.py
bayeslibs/samples/chapter5/chapter5_5.py
bayeslibs/samples/chapter5/chapter5_6.py
bayeslibs/samples/chapter5/chapter5_7.py
bayeslibs/samples/chapter5/chapter5_8.py
bayeslibs/samples/chapter6/__init__.py
bayeslibs/samples/chapter6/chapter6_1.py
bayeslibs/samples/chapter6/chapter6_2.py
bayeslibs/samples/chapter6/chapter6_3.py
bayeslibs/samples/chapter6/chapter6_4.py
bayeslibs/samples/chapter6/chapter6_5.py
bayeslibs/samples/chapter6/chapter6_6.py
bayeslibs/samples/chapter7/__init__.py
bayeslibs/samples/chapter7/chapter7_1.py
bayeslibs/samples/chapter7/chapter7_2.py
bayeslibs/samples/chapter7/chapter7_3.py
bayeslibs/utils/__init__.py
bayeslibs/utils/aiops/__init__.py
bayeslibs/utils/aiops/convert.py
bayeslibs/utils/aiops/logger.py
bayeslibs/utils/aiops/setting.py
bayeslibs/utils/aiops/system_info.py
bayeslibs-1.0.4.dist-info/LICENSE
bayeslibs-1.0.4.dist-info/METADATA
bayeslibs-1.0.4.dist-info/WHEEL
bayeslibs-1.0.4.dist-info/top_level.txt
bayeslibs-1.0.4.dist-info/RECORD
