Metadata-Version: 2.1
Name: bayeslibs
Version: 1.0.4
Summary: The bayeslibs is the best ai education libs in the world
Home-page: UNKNOWN
Author: bayes
Author-email: qianyang@aibayes.com
License: MIT
Platform: UNKNOWN
Requires-Dist: numpy
Requires-Dist: PyYAML
